crccheckcopyutil/__init__.py
crccheckcopyutil/__main__.py
crccheckcopyutil/lib/CrcCheckCopy.exe
crccheckcopyutil/lib/__init__.py
crccheckcopyutil-1.0.1.dist-info/LICENSE
crccheckcopyutil-1.0.1.dist-info/METADATA
crccheckcopyutil-1.0.1.dist-info/WHEEL
crccheckcopyutil-1.0.1.dist-info/entry_points.txt
crccheckcopyutil-1.0.1.dist-info/top_level.txt
crccheckcopyutil-1.0.1.dist-info/RECORD
