Metadata-Version: 2.1
Name: crccheckcopyutil
Version: 1.0.1
Author-email: Carlos Florez <carlos@florez.co.uk>
Maintainer-email: Carlos Florez <carlos@florez.co.uk>
License: MIT License
Project-URL: Repository, https://github.com/florez-carlos/crccheckcopyutil
Classifier: Development Status :: 5 - Production/Stable
Classifier: Programming Language :: Python :: 3.11
Requires-Python: >=3.11.6
License-File: LICENSE
